lua_to_exe/__init__.py
lua_to_exe/lua_to_exe.py
lua_to_exe/srlua/5.1-32/srglue.exe
lua_to_exe/srlua/5.1-32/srlua.exe
lua_to_exe/srlua/5.1-64/srglue.exe
lua_to_exe/srlua/5.1-64/srlua.exe
lua_to_exe/srlua/5.1.1-32/srglue.exe
lua_to_exe/srlua/5.1.1-32/srlua.exe
lua_to_exe/srlua/5.1.1-64/srglue.exe
lua_to_exe/srlua/5.1.1-64/srlua.exe
lua_to_exe/srlua/5.1.2-32/srglue.exe
lua_to_exe/srlua/5.1.2-32/srlua.exe
lua_to_exe/srlua/5.1.2-64/srglue.exe
lua_to_exe/srlua/5.1.2-64/srlua.exe
lua_to_exe/srlua/5.1.3-32/srglue.exe
lua_to_exe/srlua/5.1.3-32/srlua.exe
lua_to_exe/srlua/5.1.3-64/srglue.exe
lua_to_exe/srlua/5.1.3-64/srlua.exe
lua_to_exe/srlua/5.1.4-32/srglue.exe
lua_to_exe/srlua/5.1.4-32/srlua.exe
lua_to_exe/srlua/5.1.4-64/srglue.exe
lua_to_exe/srlua/5.1.4-64/srlua.exe
lua_to_exe/srlua/5.1.5-32/srglue.exe
lua_to_exe/srlua/5.1.5-32/srlua.exe
lua_to_exe/srlua/5.1.5-64/srglue.exe
lua_to_exe/srlua/5.1.5-64/srlua.exe
lua_to_exe/srlua/5.2.0-32/srglue.exe
lua_to_exe/srlua/5.2.0-32/srlua.exe
lua_to_exe/srlua/5.2.0-64/srglue.exe
lua_to_exe/srlua/5.2.0-64/srlua.exe
lua_to_exe/srlua/5.2.1-32/srglue.exe
lua_to_exe/srlua/5.2.1-32/srlua.exe
lua_to_exe/srlua/5.2.1-64/srglue.exe
lua_to_exe/srlua/5.2.1-64/srlua.exe
lua_to_exe/srlua/5.2.2-32/srglue.exe
lua_to_exe/srlua/5.2.2-32/srlua.exe
lua_to_exe/srlua/5.2.2-64/srglue.exe
lua_to_exe/srlua/5.2.2-64/srlua.exe
lua_to_exe/srlua/5.2.3-32/srglue.exe
lua_to_exe/srlua/5.2.3-32/srlua.exe
lua_to_exe/srlua/5.2.3-64/srglue.exe
lua_to_exe/srlua/5.2.3-64/srlua.exe
lua_to_exe/srlua/5.2.4-32/srglue.exe
lua_to_exe/srlua/5.2.4-32/srlua.exe
lua_to_exe/srlua/5.2.4-64/srglue.exe
lua_to_exe/srlua/5.2.4-64/srlua.exe
lua_to_exe/srlua/5.3.0-32/srglue.exe
lua_to_exe/srlua/5.3.0-32/srlua.exe
lua_to_exe/srlua/5.3.0-64/srglue.exe
lua_to_exe/srlua/5.3.0-64/srlua.exe
lua_to_exe/srlua/5.3.1-32/srglue.exe
lua_to_exe/srlua/5.3.1-32/srlua.exe
lua_to_exe/srlua/5.3.1-64/srglue.exe
lua_to_exe/srlua/5.3.1-64/srlua.exe
lua_to_exe/srlua/5.3.2-32/srglue.exe
lua_to_exe-1.0.dist-info/METADATA
lua_to_exe-1.0.dist-info/WHEEL
lua_to_exe-1.0.dist-info/entry_points.txt
lua_to_exe-1.0.dist-info/top_level.txt
lua_to_exe-1.0.dist-info/RECORD
