Metadata-Version: 2.1
Name: lua-to-exe
Version: 1.0
Summary: Convert Lua scripts into standalone .exe executables with ready-to-use tools and libraries.
Home-page: https://github.com/Water-Run/luaToEXE
Author: WaterRun
Author-email: 2263633954@qq.com
Classifier: Programming Language :: Python :: 3
Classifier: Programming Language :: Python :: 3.7
Classifier: Programming Language :: Python :: 3.8
Classifier: Programming Language :: Python :: 3.9
Classifier: Programming Language :: Python :: 3.10
Classifier: License :: OSI Approved :: MIT License
Classifier: Operating System :: Microsoft :: Windows
Classifier: Intended Audience :: Developers
Classifier: Topic :: Software Development :: Build Tools
Classifier: Topic :: Software Development :: Libraries :: Python Modules
Requires-Python: >=3.7
